aicrowd_api/__init__.py
aicrowd_api/aicrowd_api.py
aicrowd_api/events.py
aicrowd_api/exceptions.py
aicrowd_api/helpers.py
aicrowd_api/submission.py
aicrowd_api-0.1.25.dist-info/LICENSE
aicrowd_api-0.1.25.dist-info/METADATA
aicrowd_api-0.1.25.dist-info/WHEEL
aicrowd_api-0.1.25.dist-info/top_level.txt
aicrowd_api-0.1.25.dist-info/RECORD
