Metadata-Version: 2.1
Name: aicrowd-api
Version: 0.1.25
Summary: Python api for interacting with AIcrowd Grading infrastructure
Home-page: https://github.com/AIcrowd/aicrowd_api
Author: S.P. Mohanty
Author-email: mohanty@aicrowd.com
License: GNU General Public License v3
Keywords: aicrowd_api aicrowd crowdai_api crowdai
Classifier: Development Status :: 2 - Pre-Alpha
Classifier: Intended Audience :: Developers
Classifier: License :: OSI Approved :: GNU General Public License v3 (GPLv3)
Classifier: Natural Language :: English
Classifier: Programming Language :: Python :: 2
Classifier: Programming Language :: Python :: 2.7
Classifier: Programming Language :: Python :: 3
Classifier: Programming Language :: Python :: 3.4
Classifier: Programming Language :: Python :: 3.5
Classifier: Programming Language :: Python :: 3.6
License-File: LICENSE
Requires-Dist: requests >=2.18.4
Requires-Dist: redis
